aiovk2/__init__.py
aiovk2/api.py
aiovk2/drivers.py
aiovk2/exceptions.py
aiovk2/longpoll.py
aiovk2/mixins.py
aiovk2/parser.py
aiovk2/pools.py
aiovk2/sessions.py
aiovk2/shaping.py
tests/__init__.py
tests/utils.py
tests/functional/__init__.py
tests/functional/conftest.py
tests/functional/test_drivers.py
tests/functional/test_longpool.py
tests/functional/test_sessions.py
tests/unit/__init__.py
tests/unit/test_api.py
tests/unit/test_longpool.py
tests/unit/test_pools.py
tests/unit/test_shaping.py
aiovk2-1.0.0.dist-info/LICENSE
aiovk2-1.0.0.dist-info/METADATA
aiovk2-1.0.0.dist-info/WHEEL
aiovk2-1.0.0.dist-info/top_level.txt
aiovk2-1.0.0.dist-info/RECORD
